Bayesian2D/Bayesian2D_scr.py
Bayesian2D/__init__.py
Bayesian2D/scripts/Bayesian2D_scr.py
Bayesian2D/scripts/__init__.py
Bayesian2D/tests/__init__.py
Bayesian2D/tests/test_Bayesian2D.py
Bayesian2D/tests/test_acquisition.py
Bayesian2D/tests/test_create_random.py
Bayesian2D/tests/test_fit_model.py
Bayesian2D/tests/test_functions.py
Bayesian2D/tests/test_initial_points.py
Bayesian2D/tests/test_optimize.py
Bayesian2D/tests/test_plot.py
Bayesian2D/tests/test_results.py
Bayesian2D/tests/test_surrogate.py
Bayesian2D/tools/Bayesian2D.py
Bayesian2D/tools/__init__.py
Bayesian2D/tools/acquisition.py
Bayesian2D/tools/create_random.py
Bayesian2D/tools/fit_model.py
Bayesian2D/tools/functions.py
Bayesian2D/tools/initial_points.py
Bayesian2D/tools/optimize.py
Bayesian2D/tools/plot.py
Bayesian2D/tools/results.py
Bayesian2D/tools/surrogate.py
Bayesian2D-0.3.1.dist-info/LICENSE
Bayesian2D-0.3.1.dist-info/METADATA
Bayesian2D-0.3.1.dist-info/WHEEL
Bayesian2D-0.3.1.dist-info/top_level.txt
Bayesian2D-0.3.1.dist-info/RECORD
