Metadata-Version: 2.1
Name: Bayesian2D
Version: 0.3.1
Summary: Package used to find the maximum or minimum of any 2D function using Bayesian optimization
Home-page: https://github.com/JRaidal/Bayesian2D
Author: Juhan Raidal
Author-email: juhantiitus.raidal@gmail.com
License: MIT
Platform: UNKNOWN
Requires-Dist: numpy
Requires-Dist: datetime
Requires-Dist: scipy
Requires-Dist: sklearn
Requires-Dist: matplotlib
